medcom_ble/__init__.py
medcom_ble/const.py
medcom_ble/parser.py
medcom_ble-0.1.1.dist-info/LICENSE
medcom_ble-0.1.1.dist-info/METADATA
medcom_ble-0.1.1.dist-info/WHEEL
medcom_ble-0.1.1.dist-info/RECORD
